{
  "sources": [
    "https://anidb.net/anime/7822",
    "https://anime-planet.com/anime/hello-kitty-no-hansel-to-gretel",
    "https://anisearch.com/anime/6415",
    "https://kitsu.io/anime/9306",
    "https://myanimelist.net/anime/22489",
    "https://notify.moe/anime/e-RBpFmmg"
  ],
  "synopsis": {
    "text": "",
    "author": "mistral.mistral-large-2402-v1:0",
    "lastUpdate": "2024-06-22"
  },
  "score": {
    "arithmeticMean": 5.478024489795918,
    "arithmeticGeometricMean": 5.444279371332039,
    "median": 5.0,
    "lastUpdate": "2024-05-08"
  }
}