{
  "sources": [
    "https://anilist.co/anime/6945",
    "https://anime-planet.com/anime/gintama-jump-festa-2008",
    "https://anisearch.com/anime/5529",
    "https://kitsu.io/anime/4797",
    "https://livechart.me/anime/3999",
    "https://myanimelist.net/anime/6945",
    "https://notify.moe/anime/WwnRtKiiR"
  ],
  "synopsis": {
    "text": "",
    "author": "mistral.mistral-large-2402-v1:0",
    "lastUpdate": "2024-05-14"
  },
  "score": {
    "arithmeticMean": 8.119612686633094,
    "arithmeticGeometricMean": 8.118821055193647,
    "median": 8.09090909090909,
    "lastUpdate": "2024-05-06"
  }
}