{
  "sources": [
    "https://anilist.co/anime/110579",
    "https://anime-planet.com/anime/fragments",
    "https://myanimelist.net/anime/39536"
  ],
  "synopsis": {
    "text": "",
    "author": "mistral.mistral-large-2402-v1:0",
    "coAuthors": [],
    "hash": "13c3bf0224ade359",
    "created": "2024-05-12",
    "lastUpdate": "2024-05-12"
  },
  "score": {
    "arithmeticMean": 6.0574545454545445,
    "arithmeticGeometricMean": 6.049212262241175,
    "median": 5.85,
    "hash": "13c3bf0224ade359",
    "lastUpdate": "2024-05-07"
  }
}