{
  "sources": [
    "https://anilist.co/anime/114915",
    "https://kitsu.io/anime/46302",
    "https://myanimelist.net/anime/51531"
  ],
  "synopsis": {
    "text": "",
    "author": "mistral.mistral-large-2402-v1:0",
    "coAuthors": [],
    "hash": "1ac64d094f374cb3",
    "created": "2024-05-14",
    "lastUpdate": "2024-05-14"
  },
  "score": {
    "arithmeticMean": 5.300909090909091,
    "arithmeticGeometricMean": 5.300240107438778,
    "median": 5.300909090909091,
    "hash": "1ac64d094f374cb3",
    "lastUpdate": "2024-05-05"
  }
}