{
  "sources": [
    "https://anidb.net/anime/9342",
    "https://anilist.co/anime/14967",
    "https://anime-planet.com/anime/haganai-i-dont-have-many-friends-next",
    "https://anisearch.com/anime/7966",
    "https://kitsu.io/anime/7190",
    "https://livechart.me/anime/876",
    "https://myanimelist.net/anime/14967",
    "https://notify.moe/anime/6NxdtKimR"
  ],
  "score": {
    "arithmeticMean": 7.436154888590665,
    "arithmeticGeometricMean": 7.434861610269781,
    "median": 7.425140890169709,
    "hash": "1ca088106d07ce9e",
    "lastUpdate": "2024-05-09"
  }
}