{
  "sources": [
    "https://anidb.net/anime/10869",
    "https://anilist.co/anime/20921",
    "https://anime-planet.com/anime/cardfight-vanguard-g",
    "https://anisearch.com/anime/9959",
    "https://kitsu.io/anime/9781",
    "https://livechart.me/anime/1222",
    "https://myanimelist.net/anime/27815",
    "https://notify.moe/anime/mAXLtFiiR"
  ],
  "synopsis": {
    "text": "Capital ize on a fresh era of Cardfighting with Chrono Shindou, an ordinary middle school student with an intimidating appearance but a gentle heart. One day, Chrono stumbles upon an enigmatic Cardfight deck, Gear Chronicle, in his locker. He ventures to the nearby Card Capital 2, where he encounters Kamui Katsuragi, who introduces him to the world of Vanguard.\n\nUnder Kamui's guidance, Chrono embarks on a thrilling journey, making friends and rivals along the way. Among them are his future teammates, Shion Kiba and Tokoha Anjou. As they bond over their shared passion for the game, Chrono and his friends strive to become the new generation of champions.\n\nThree years after Aichi and his friends have moved on, Misaki now owns another Card Capital branch, with Kamui working part-time. Chrono, armed with his rare Gear Chronicle deck, stands up to face formidable opponents, forging new friendships and rivalries in this captivating world of strategic card battles. Join Chrono and his friends as they shape their destinies and unravel the mysteries of the 'impossible future' in this new chapter of Cardfighting.",
    "author": "mistral.mistral-large-2402-v1:0",
    "coAuthors": [],
    "hash": "2407eda73eee55cb",
    "created": "2023-10-19",
    "lastUpdate": "2023-10-19"
  },
  "score": {
    "arithmeticMean": 6.634975185528757,
    "arithmeticGeometricMean": 6.621252188124528,
    "median": 6.658673469387756,
    "hash": "2407eda73eee55cb",
    "lastUpdate": "2024-05-09"
  }
}