{
  "sources": [
    "https://anilist.co/anime/17409",
    "https://anime-planet.com/anime/say-i-love-you-mei-and-marshmallow",
    "https://anisearch.com/anime/8546",
    "https://kitsu.io/anime/7779",
    "https://livechart.me/anime/4403",
    "https://myanimelist.net/anime/17409",
    "https://notify.moe/anime/GgpppKimR"
  ],
  "synopsis": {
    "text": "",
    "author": "mistral.mistral-large-2402-v1:0",
    "coAuthors": [],
    "hash": "2af7c2ee617fcd4e",
    "created": "2024-05-15",
    "lastUpdate": "2024-05-15"
  },
  "score": {
    "arithmeticMean": 6.374514415289926,
    "arithmeticGeometricMean": 6.343306942300465,
    "median": 6.636363636363637,
    "hash": "2af7c2ee617fcd4e",
    "lastUpdate": "2024-05-10"
  }
}