{
  "sources": [
    "https://anidb.net/anime/12311",
    "https://anilist.co/anime/102431",
    "https://anime-planet.com/anime/dragon-ball-z-the-real-4-d",
    "https://anisearch.com/anime/11653",
    "https://kitsu.io/anime/13123",
    "https://livechart.me/anime/8029",
    "https://notify.moe/anime/C5FMhFmmg"
  ],
  "synopsis": {
    "text": "",
    "author": "mistral.mistral-large-2402-v1:0"
  },
  "score": {
    "arithmeticMean": 5.707385281385282,
    "arithmeticGeometricMean": 5.6766757632352345,
    "median": 5.98051948051948
  },
  "lastUpdate": "2024-05-09"
}