{
  "sources": [
    "https://anilist.co/anime/102168",
    "https://anime-planet.com/anime/fushigi-na-somera-chan-special",
    "https://anisearch.com/anime/16911",
    "https://kitsu.io/anime/12775",
    "https://livechart.me/anime/8855",
    "https://myanimelist.net/anime/33659",
    "https://notify.moe/anime/KRRZhFmmR"
  ],
  "synopsis": {
    "text": "",
    "author": "mistral.mistral-large-2402-v1:0"
  },
  "score": {
    "arithmeticMean": 5.80873964131107,
    "arithmeticGeometricMean": 5.7916650328715225,
    "median": 5.615491651205936
  },
  "lastUpdate": "2024-05-06"
}