{
  "sources": [
    "https://anidb.net/anime/475",
    "https://anilist.co/anime/1728",
    "https://anime-planet.com/anime/super-gals",
    "https://anisearch.com/anime/3136",
    "https://kitsu.io/anime/1549",
    "https://livechart.me/anime/5433",
    "https://myanimelist.net/anime/1728",
    "https://notify.moe/anime/6OvB5KmmR"
  ],
  "score": {
    "arithmeticMean": 7.210429366551815,
    "arithmeticGeometricMean": 7.209562615305955,
    "median": 7.24,
    "hash": "3d84297776f51716",
    "lastUpdate": "2024-05-10"
  }
}