{
  "sources": [
    "https://anidb.net/anime/3170",
    "https://anilist.co/anime/612",
    "https://anime-planet.com/anime/petopeto-san",
    "https://anisearch.com/anime/3218",
    "https://kitsu.io/anime/567",
    "https://livechart.me/anime/7438",
    "https://myanimelist.net/anime/612",
    "https://notify.moe/anime/9I3T5FmmR"
  ],
  "score": {
    "arithmeticMean": 6.319731071649438,
    "arithmeticGeometricMean": 6.308140878619879,
    "median": 6.298,
    "hash": "5256f3e8d3ab42db",
    "lastUpdate": "2024-05-09"
  }
}