{
  "sources": [
    "https://anime-planet.com/anime/kensaku-to-enjin-no-abc-days",
    "https://kitsu.io/anime/41710",
    "https://myanimelist.net/anime/37017"
  ],
  "synopsis": {
    "text": "",
    "author": "mistral.mistral-large-2402-v1:0",
    "coAuthors": [],
    "hash": "541da0b734c9e7df",
    "created": "2024-05-14",
    "lastUpdate": "2024-05-14"
  },
  "score": {
    "arithmeticMean": 6.806,
    "arithmeticGeometricMean": 6.806,
    "median": 6.806,
    "hash": "541da0b734c9e7df",
    "lastUpdate": "2024-05-08"
  }
}