{
  "sources": [
    "https://anidb.net/anime/3563",
    "https://anilist.co/anime/4663",
    "https://anime-planet.com/anime/tekken-chinmi",
    "https://anisearch.com/anime/3032",
    "https://kitsu.io/anime/3729",
    "https://myanimelist.net/anime/4663",
    "https://notify.moe/anime/-_Z95FiiR"
  ],
  "synopsis": {
    "text": "",
    "author": "mistral.mistral-large-2402-v1:0",
    "lastUpdate": "2024-05-15"
  },
  "score": {
    "arithmeticMean": 6.858789822422476,
    "arithmeticGeometricMean": 6.85020324994528,
    "median": 7.046,
    "lastUpdate": "2024-05-08"
  }
}