{
  "sources": [
    "https://anidb.net/anime/7442",
    "https://anilist.co/anime/8456",
    "https://anime-planet.com/anime/queens-blade-beautiful-warriors",
    "https://anisearch.com/anime/6193",
    "https://kitsu.io/anime/5342",
    "https://livechart.me/anime/4947",
    "https://myanimelist.net/anime/8456",
    "https://notify.moe/anime/PihmtKimg"
  ],
  "score": {
    "arithmeticMean": 6.387540455576169,
    "arithmeticGeometricMean": 6.3734383970677495,
    "median": 6.3968181818181815,
    "hash": "73e15bbf1275a809",
    "lastUpdate": "2024-05-09"
  }
}