{
  "sources": [
    "https://anidb.net/anime/15502",
    "https://anilist.co/anime/117533",
    "https://anime-planet.com/anime/cells-at-work-code-black",
    "https://anisearch.com/anime/15229",
    "https://kitsu.io/anime/43167",
    "https://livechart.me/anime/9890",
    "https://myanimelist.net/anime/41694",
    "https://notify.moe/anime/gz1czleZg"
  ],
  "synopsis": {
    "text": "As the relentless grind of daily life takes its toll on a human body, the cells within it are thrust into a chaotic and perilous work environment. Amidst this turmoil, a rookie Red Blood Cell, Sekkekkyuu AA2153, and a seasoned White Blood Cell, Hakkekkyuu U-1196, are tasked with the daunting responsibility of maintaining the body's health. As the Red Blood Cell races against time to deliver oxygen, the White Blood Cell wages war against invading viruses and bacteria. But their challenges don't end there. The human's poor lifestyle choices, including excessive drinking, smoking, and sleep deprivation, exacerbate the cells' already demanding jobs, pushing their world to the brink of a Code Black. Despite the seemingly insurmountable odds, these cells must persevere in their roles, facing a myriad of health issues such as ulcers, fatty liver, and erectile dysfunction. This is a gripping tale of survival and resilience, set within the intricate and often treacherous landscape of the human body. Will the cells' unwavering determination be enough to keep their world from spiraling into chaos? Only time will tell.",
    "author": "mistral.mistral-large-2402-v1:0",
    "coAuthors": [],
    "hash": "7407cb8bf36a1690",
    "created": "2024-05-12",
    "lastUpdate": "2024-05-12"
  },
  "score": {
    "arithmeticMean": 7.58842926716141,
    "arithmeticGeometricMean": 7.587765074307697,
    "median": 7.611989795918367,
    "hash": "7407cb8bf36a1690",
    "lastUpdate": "2024-05-09"
  }
}