{
  "sources": [
    "https://anidb.net/anime/18089",
    "https://anilist.co/anime/166611",
    "https://anime-planet.com/anime/natsumes-book-of-friends-season-7",
    "https://anisearch.com/anime/18506",
    "https://kitsu.io/anime/47678",
    "https://livechart.me/anime/12234",
    "https://myanimelist.net/anime/55823",
    "https://notify.moe/anime/LkRJEF94g"
  ],
  "synopsis": {
    "text": "",
    "author": "mistral.mistral-large-2402-v1:0",
    "coAuthors": [],
    "hash": "7468f2de05cd5c78",
    "created": "2024-05-12",
    "lastUpdate": "2024-05-12"
  },
  "score": {
    "arithmeticMean": 0.0,
    "arithmeticGeometricMean": 0.0,
    "median": 0.0,
    "hash": "7468f2de05cd5c78",
    "lastUpdate": "2024-05-11"
  }
}