{
  "sources": [
    "https://anidb.net/anime/1393",
    "https://anilist.co/anime/2277",
    "https://anime-planet.com/anime/magical-play",
    "https://anisearch.com/anime/2821",
    "https://kitsu.io/anime/2062",
    "https://livechart.me/anime/12028",
    "https://myanimelist.net/anime/2277",
    "https://notify.moe/anime/D2FPcKmmR"
  ],
  "synopsis": {
    "text": "Along side her sentient, fish-like attire, Uokichi, the ambitious and spirited young witch, Padudu, embarks on an exhilarating journey to achieve her ultimate dream: becoming a magical girl and visiting Earth. Representing her quaint aquatic village, Sea Heaven, Padudu must prove her worth as a battle magician by gathering coveted flower tokens in amphitheater battles.\n\nJoined by a motley crew of fellow dreamers, including the mischievous Pipin, the cunning Myumyu, and the enigmatic Nonononn, Padudu's adventures lead her through various challenges and encounters. However, their thrilling escapades are shadowed by the relentless pursuit of the malevolent Queen Purilun and her loyal minion, Zucchini.\n\nThroughout her quest, Padudu faces unexpected obstacles, such as being imprisoned in Dance Valley's dungeon by the devious Mayor Koffy. But in the depths of her captivity, she crosses paths with the mysterious witch, Nonononn, and the two unite in a spectacular battle for survival.\n\nFrom the coliseums to the whimsical Sweetland, Padudu's determination never wavers as she competes against her rivals to collect the precious hanamaru. Will Padudu and her newfound friends successfully outwit Queen Purilun and realize their dreams of becoming magical girls on Earth? Join them in the enchanting world of Mahou Yugi to find out!",
    "author": "mistral.mistral-large-2402-v1:0",
    "lastUpdate": "2024-05-09"
  },
  "score": {
    "arithmeticMean": 6.291622581500131,
    "arithmeticGeometricMean": 6.287363659912776,
    "median": 6.25,
    "lastUpdate": "2024-05-09"
  }
}