{
  "sources": [
    "https://anilist.co/anime/102595",
    "https://anime-planet.com/anime/koncos-the-starry-night",
    "https://anisearch.com/anime/13633",
    "https://kitsu.io/anime/41183",
    "https://myanimelist.net/anime/37683",
    "https://notify.moe/anime/hRQgnNMmR"
  ],
  "synopsis": {
    "text": "",
    "author": "mistral.mistral-large-2402-v1:0",
    "lastUpdate": "2024-06-22"
  },
  "score": {
    "arithmeticMean": 5.13495918367347,
    "arithmeticGeometricMean": 5.08977617721772,
    "median": 5.145,
    "lastUpdate": "2024-05-06"
  }
}