{
  "sources": [
    "https://anidb.net/anime/7956",
    "https://anilist.co/anime/9907",
    "https://anime-planet.com/anime/bokura-no-live-kimi-to-no-life",
    "https://anisearch.com/anime/6518",
    "https://kitsu.io/anime/5935",
    "https://myanimelist.net/anime/9907",
    "https://notify.moe/anime/RerGpKmmR"
  ],
  "synopsis": {
    "text": "",
    "author": "mistral.mistral-large-2402-v1:0",
    "lastUpdate": "2024-05-14"
  },
  "score": {
    "arithmeticMean": 6.799556321229791,
    "arithmeticGeometricMean": 6.793674894216262,
    "median": 7.0,
    "lastUpdate": "2024-05-07"
  }
}