{
  "sources": [
    "https://anidb.net/anime/5290",
    "https://anilist.co/anime/15957",
    "https://anime-planet.com/anime/dokachin",
    "https://anisearch.com/anime/4348",
    "https://kitsu.io/anime/7346",
    "https://livechart.me/anime/11666",
    "https://myanimelist.net/anime/15957",
    "https://notify.moe/anime/bbDKpKimg"
  ],
  "synopsis": {
    "text": "Kakaka, Tototo, and their primitive son, Dokachin, find themselves thrust into the bustling world of 1960's Japan when a time machine experiment goes awry, teleporting them and a piece of their land into the future. As the Dokachin family grapples with the unfamiliar sights and sounds of their new surroundings, they inadvertently wreak havoc with their stone axes, sparking a series of chaotic misadventures. Each episode of this comedic anime features two stories centered around the family's attempts to adapt to modern life while leaving their own unique mark on the neighborhood.",
    "author": "mistral.mistral-large-2402-v1:0",
    "lastUpdate": "2024-05-09"
  },
  "score": {
    "arithmeticMean": 4.775356215213359,
    "arithmeticGeometricMean": 4.648932969089635,
    "median": 4.818181818181818,
    "lastUpdate": "2024-05-09"
  }
}