{
  "sources": [
    "https://anidb.net/anime/10912",
    "https://anilist.co/anime/104106",
    "https://anime-planet.com/anime/mix-master-final-force",
    "https://anisearch.com/anime/10217",
    "https://kitsu.io/anime/11214",
    "https://myanimelist.net/anime/31246",
    "https://notify.moe/anime/ObCutFmmg"
  ],
  "score": {
    "arithmeticMean": 5.544472727272728,
    "arithmeticGeometricMean": 5.494006088033509,
    "median": 5.0,
    "hash": "c27c04213ccb33b1",
    "lastUpdate": "2024-05-07"
  }
}