{
  "sources": [
    "https://anilist.co/anime/174938",
    "https://kitsu.io/anime/48858"
  ],
  "synopsis": {
    "text": "",
    "author": "mistral.mistral-large-2402-v1:0",
    "coAuthors": [],
    "hash": "c5e6364a17f709f0",
    "created": "2024-05-17",
    "lastUpdate": "2024-05-17"
  },
  "score": {
    "arithmeticMean": 7.454545454545454,
    "arithmeticGeometricMean": 7.454545454545454,
    "median": 7.454545454545454,
    "hash": "c5e6364a17f709f0",
    "lastUpdate": "2024-05-17"
  }
}