{
  "sources": [
    "https://anidb.net/anime/14095",
    "https://anime-planet.com/anime/cocomong-2",
    "https://anisearch.com/anime/13293",
    "https://kitsu.io/anime/41865",
    "https://myanimelist.net/anime/37943"
  ],
  "synopsis": {
    "text": "",
    "author": "mistral.mistral-large-2402-v1:0",
    "coAuthors": [],
    "hash": "dc5997f5f84a85a5",
    "created": "2024-05-14",
    "lastUpdate": "2024-05-14"
  },
  "score": {
    "arithmeticMean": 6.688,
    "arithmeticGeometricMean": 6.688,
    "median": 6.688,
    "hash": "dc5997f5f84a85a5",
    "lastUpdate": "2024-05-08"
  }
}