{
  "sources": [
    "https://anidb.net/anime/398",
    "https://anilist.co/anime/791",
    "https://anime-planet.com/anime/arion",
    "https://anisearch.com/anime/2005",
    "https://kitsu.io/anime/706",
    "https://livechart.me/anime/6492",
    "https://myanimelist.net/anime/791",
    "https://notify.moe/anime/OPJAcFimg"
  ],
  "score": {
    "arithmeticMean": 5.962630267691492,
    "arithmeticGeometricMean": 5.940889012361293,
    "median": 6.096,
    "hash": "e6a2ae1f25bb30f9",
    "lastUpdate": "2024-05-08"
  }
}