{
  "sources": [
    "https://anidb.net/anime/8060",
    "https://anilist.co/anime/9774",
    "https://anime-planet.com/anime/morita-san-wa-mukuchi",
    "https://anisearch.com/anime/6592",
    "https://kitsu.io/anime/5860",
    "https://livechart.me/anime/4992",
    "https://myanimelist.net/anime/9774",
    "https://notify.moe/anime/Nx-GtKmiR"
  ],
  "score": {
    "arithmeticMean": 6.4410352504638215,
    "arithmeticGeometricMean": 6.430756217829075,
    "median": 6.524,
    "hash": "e92837279dd32147",
    "lastUpdate": "2024-05-09"
  }
}